<?xml version="1.0" encoding="UTF-8"?>

<!-- Note: All tests mentioned here are just for reference purpose & they do not exist in 'src', as this file is meant for template purpose. Based on our context we need to update test names appropriately. -->

<suite name="Json" parallel="false">

	<test name="ExtractJsonApiEx1_GetRequest_HttpBinOrgSite">
		<classes>
			<class name="webMainScripts.jsonApiExamples.ExtractJsonApiEx1_GetRequest_HttpBinOrgSite" />
		</classes>
	</test> <!-- Test1 -->

	<test name="CopyOfExtractJsonApiEx1_GetRequest_HttpBinOrgSite">
		<classes>
			<class name="webMainScripts.jsonApiExamples.CopyOfExtractJsonApiEx1_GetRequest_HttpBinOrgSite" />
		</classes>
	</test> <!-- Test2 -->

</suite> <!-- Suite -->